__init__.py
ted_repo-0.0.9.dist-info/licenses/LICENSE
tools/apply_lora.py
tools/down.py
tools/get_model.py
tools/push.py
tools/send_email.py
ted_repo-0.0.9.dist-info/METADATA
ted_repo-0.0.9.dist-info/WHEEL
ted_repo-0.0.9.dist-info/top_level.txt
ted_repo-0.0.9.dist-info/RECORD
