Metadata-Version: 2.4
Name: ted_repo
Version: 0.0.9
Summary: A small example package
Author-email: pinsu <757469399@qq.com>
Classifier: Programming Language :: Python :: 3
Classifier: License :: OSI Approved :: MIT License
Classifier: Operating System :: OS Independent
Requires-Python: >=3.8
License-File: LICENSE
Requires-Dist: huggingface_hub==0.26.2
Dynamic: license-file
